Journal_Indexer/__init__.py
Journal_Indexer/journal_command_runner.py
Journal_Indexer-1.0.dist-info/LICENSE
Journal_Indexer-1.0.dist-info/METADATA
Journal_Indexer-1.0.dist-info/WHEEL
Journal_Indexer-1.0.dist-info/entry_points.txt
Journal_Indexer-1.0.dist-info/top_level.txt
Journal_Indexer-1.0.dist-info/RECORD
